vantetider/__init__.py
vantetider/allowed_values.py
vantetider/scraper.py
vantetider_scraper-0.2.0.dist-info/LICENSE
vantetider_scraper-0.2.0.dist-info/METADATA
vantetider_scraper-0.2.0.dist-info/WHEEL
vantetider_scraper-0.2.0.dist-info/top_level.txt
vantetider_scraper-0.2.0.dist-info/RECORD
