Metadata-Version: 2.1
Name: vantetider-scraper
Version: 0.2.0
Summary: A scraper of statistical data from Vantetider.se built on top of Statscraper.
Home-page: https://github.com/jplusplus/vantetider-scraper
Author: Jens Finnäs
Author-email: jens.finnas@gmail.com
License: MIT
Download-URL: https://github.com/jplusplus/vantetider-scraper/archive/0.2.0.tar.gz
Platform: UNKNOWN
Requires-Dist: requests
Requires-Dist: requests-cache
Requires-Dist: BeautifulSoup4
